Metadata-Version: 2.1
Name: palettepy
Version: 1.0.0
Summary: helps you to print colored text in easy way and has support to rgb colors
Home-page: https://www.linkedin.com/in/mario-nageh-744b67116/
Download-URL: https://github.com/user/reponame/archive/v_01.tar.gz
Author: Mario Nageh
Author-email: marionageh7@gmail.com
License: MIT
Keywords: COLORS,PRINTING,STYLES
Classifier: Intended Audience :: Developers
Classifier: Topic :: Software Development :: Build Tools
Classifier: License :: OSI Approved :: MIT License
Classifier: License :: OSI Approved :: MIT License
Classifier: Programming Language :: Python
Classifier: Programming Language :: Python :: 3
Classifier: Programming Language :: Python :: 3.6
Classifier: Programming Language :: Python :: 3.7
Classifier: Programming Language :: Python :: 3.8
Classifier: Programming Language :: Python :: 3.9
Classifier: Operating System :: OS Independent
License-File: LICENSE.txt
